{
  "hash": "fcd1c9ed",
  "configHash": "b49465a0",
  "lockfileHash": "28f0a53c",
  "browserHash": "43da7781",
  "optimized": {
    "react": {
      "src": "../../node_modules/react/index.js",
      "file": "react.js",
      "fileHash": "7790c66f",
      "needsInterop": true
    },
    "react-dom/client": {
      "src": "../../node_modules/react-dom/client.js",
      "file": "react-dom_client.js",
      "fileHash": "034845af",
      "needsInterop": true
    },
    "react-router-dom": {
      "src": "../../node_modules/react-router-dom/dist/index.js",
      "file": "react-router-dom.js",
      "fileHash": "3c1f99de",
      "needsInterop": false
    },
    "axios": {
      "src": "../../node_modules/axios/index.js",
      "file": "axios.js",
      "fileHash": "c8e7c2be",
      "needsInterop": false
    },
    "leaflet": {
      "src": "../../node_modules/leaflet/dist/leaflet-src.js",
      "file": "leaflet.js",
      "fileHash": "058eda9a",
      "needsInterop": true
    }
  },
  "chunks": {
    "chunk-V2X5ZORR": {
      "file": "chunk-V2X5ZORR.js"
    },
    "chunk-32E4H3EV": {
      "file": "chunk-32E4H3EV.js"
    },
    "chunk-G3PMV62Z": {
      "file": "chunk-G3PMV62Z.js"
    }
  }
}